satel_integra/__init__.py
satel_integra/cli.py
satel_integra/satel_integra.py
satel_integra-0.3.7.dist-info/AUTHORS.rst
satel_integra-0.3.7.dist-info/LICENSE
satel_integra-0.3.7.dist-info/METADATA
satel_integra-0.3.7.dist-info/WHEEL
satel_integra-0.3.7.dist-info/entry_points.txt
satel_integra-0.3.7.dist-info/top_level.txt
satel_integra-0.3.7.dist-info/RECORD
