Metadata-Version: 2.1
Name: satel-integra
Version: 0.3.7
Summary: Communication library and basic testing tool for Satel Integra alarm system. Communication via tcpip protocol published by SATEL. 
Home-page: https://github.com/c-soft/satel_integra
Author: Krzysztof Machelski
Author-email: krzysztof.machelski+pypi@gmail.com
License: MIT license
Keywords: satel_integra
Classifier: Development Status :: 2 - Pre-Alpha
Classifier: Intended Audience :: Developers
Classifier: License :: OSI Approved :: MIT License
Classifier: Natural Language :: English
Classifier: Programming Language :: Python :: 3
Classifier: Programming Language :: Python :: 3.6
Classifier: Programming Language :: Python :: 3.7
License-File: LICENSE
License-File: AUTHORS.rst
Requires-Dist: Click (>=6.0)
